firecloud/__about__.py
firecloud/__init__.py
firecloud/api.py
firecloud/config.py
firecloud/entity.py
firecloud/errors.py
firecloud/fccore.py
firecloud/fiss.py
firecloud/method.py
firecloud/submission.py
firecloud/supervisor.py
firecloud/workspace.py
firecloud-0.16.14.dist-info/METADATA
firecloud-0.16.14.dist-info/RECORD
firecloud-0.16.14.dist-info/WHEEL
firecloud-0.16.14.dist-info/entry_points.txt
firecloud-0.16.14.dist-info/top_level.txt
