Metadata-Version: 2.1
Name: firecloud
Version: 0.16.14
Summary: Firecloud API bindings and FISS CLI
Home-page: https://github.com/broadinstitute/fiss
Author: Broad Institute CGA Genome Data Analysis Center
Author-email: gdac@broadinstitute.org
License: BSD 3-Clause License
Platform: UNKNOWN
Classifier: Programming Language :: Python :: 2
Classifier: Programming Language :: Python :: 3
Classifier: Intended Audience :: Science/Research
Classifier: Topic :: Scientific/Engineering :: Bio-Informatics
Classifier: Topic :: Scientific/Engineering :: Interface Engine/Protocol Translator
Requires-Dist: google-auth (==1.4.2)
Requires-Dist: pydot
Requires-Dist: requests[security]
Requires-Dist: six
Requires-Dist: pylint (==1.7.2)
